esocial/__init__.py
esocial/client.py
esocial/utils.py
esocial/xml.py
esocial/certs/libesocial-cert-test.pfx
esocial/certs/serpro_full_chain.pem
esocial/tests/__init__.py
esocial/tests/test_client.py
esocial/tests/test_utils.py
esocial/tests/test_xml.py
esocial/xsd/ConsultaIdentificadoresEventosEmpregador-v1_0_0.xsd
esocial/xsd/ConsultaIdentificadoresEventosTabela-v1_0_0.xsd
esocial/xsd/ConsultaIdentificadoresEventosTrabalhador-v1_0_0.xsd
esocial/xsd/ConsultaLoteEventos-v1_0_0.xsd
esocial/xsd/EnvioLoteEventos-v1_1_1.xsd
esocial/xsd/RetornoConsultaIdentificadoresEventos-v1_0_0.xsd
esocial/xsd/RetornoEnvioLoteEventos-v1_1_0.xsd
esocial/xsd/RetornoEvento-v1_2_1.xsd
esocial/xsd/RetornoProcessamentoLote-v1_3_0.xsd
esocial/xsd/RetornoSolicitacaoDownloadEventos-v1_0_0.xsd
esocial/xsd/SolicitacaoDownloadEventosPorId-v1_0_0.xsd
esocial/xsd/SolicitacaoDownloadEventosPorNrRecibo-v1_0_0.xsd
esocial/xsd/xmldsig-core-schema.xsd
esocial/xsd/v2.5.00/evtAdmPrelim.xsd
esocial/xsd/v2.5.00/evtAdmissao.xsd
esocial/xsd/v2.5.00/evtAfastTemp.xsd
esocial/xsd/v2.5.00/evtAltCadastral.xsd
esocial/xsd/v2.5.00/evtAltContratual.xsd
esocial/xsd/v2.5.00/evtAqProd.xsd
esocial/xsd/v2.5.00/evtAvPrevio.xsd
esocial/xsd/v2.5.00/evtBasesFGTS.xsd
esocial/xsd/v2.5.00/evtBasesTrab.xsd
esocial/xsd/v2.5.00/evtBenPrRP.xsd
esocial/xsd/v2.5.00/evtCAT.xsd
esocial/xsd/v2.5.00/evtCS.xsd
esocial/xsd/v2.5.00/evtCdBenPrRP.xsd
esocial/xsd/v2.5.00/evtComProd.xsd
esocial/xsd/v2.5.00/evtContrSindPatr.xsd
esocial/xsd/v2.5.00/evtContratAvNP.xsd
esocial/xsd/v2.5.00/evtConvInterm.xsd
esocial/xsd/v2.5.00/evtDeslig.xsd
esocial/xsd/v2.5.00/evtExclusao.xsd
esocial/xsd/v2.5.00/evtExpRisco.xsd
esocial/xsd/v2.5.00/evtFGTS.xsd
esocial/xsd/v2.5.00/evtFechaEvPer.xsd
esocial/xsd/v2.5.00/evtInfoComplPer.xsd
esocial/xsd/v2.5.00/evtInfoEmpregador.xsd
esocial/xsd/v2.5.00/evtIrrf.xsd
esocial/xsd/v2.5.00/evtIrrfBenef.xsd
esocial/xsd/v2.5.00/evtMonit.xsd
esocial/xsd/v2.5.00/evtPgtos.xsd
esocial/xsd/v2.5.00/evtReabreEvPer.xsd
libesocial-0.1.0.dist-info/LICENSE
libesocial-0.1.0.dist-info/METADATA
libesocial-0.1.0.dist-info/WHEEL
libesocial-0.1.0.dist-info/top_level.txt
libesocial-0.1.0.dist-info/RECORD
