Metadata-Version: 2.1
Name: libesocial
Version: 0.1.0
Summary: Biblioteca para uso com o eSocial
Home-page: https://github.com/qualitaocupacional/libesocial
Author: Qualita Seguranca e Saude Ocupacional
Author-email: lab.ti@qualitamais.com.br
License: Apache 2.0
Platform: UNKNOWN
Classifier: Development Status :: 3 - Alpha
Classifier: Intended Audience :: Developers
Classifier: License :: OSI Approved :: Apache Software License
Classifier: Programming Language :: Python :: 2.7
Classifier: Programming Language :: Python :: 3
Classifier: Programming Language :: Python :: 3.4
Classifier: Programming Language :: Python :: 3.5
Requires-Dist: dotmap (>=1.3.24)
Requires-Dist: lxml (>=4.6.3)
Requires-Dist: pyOpenSSL (>=22.1.0)
Requires-Dist: requests (>=2.26.0)
Requires-Dist: signxml (>=3.1.0)
Requires-Dist: six (>=1.11.0)
Requires-Dist: zeep (>=4.1.0)
